<?xml version="1.0" encoding="UTF-8"?>
<con:soapui-project id="2ef2e375-d514-410b-a374-ed5dd7b5db86" activeEnvironment="Default" name="REST Project 3" resourceRoot="" soapui-version="5.5.0" abortOnError="false" runType="SEQUENTIAL" encryptionMode="Not encrypted" updated="3.3.2 2020-08-19T12:03:33Z" xmlns:con="http://eviware.com/soapui/config"><con:settings/><con:interface xsi:type="con:RestService" id="aafaa6ed-9e35-4b52-b5fc-ed8aa6db7971" wadlVersion="http://wadl.dev.java.net/2009/02" name="https://petstore.swagger.io" type="rest" xmlns:xsi="http://www.w3.org/2001/XMLSchema-instance"><con:settings/><con:definitionCache type="TEXT" rootPart=""/><con:endpoints><con:endpoint>https://petstore.swagger.io</con:endpoint></con:endpoints><con:resource name="Pet" path="/v2/pet/" id="67d615a8-e0bd-473f-a6f4-4e0ede909857"><con:settings/><con:parameters><con:parameter><con:name>status</con:name><con:value/><con:style>QUERY</con:style><con:default/><con:description xsi:nil="true"/></con:parameter></con:parameters><con:method name="Pet 1" id="462eee08-d4a4-4062-a5f4-a87e0fd66936" method="GET"><con:settings/><con:parameters/><con:representation type="RESPONSE"><con:mediaType>application/json</con:mediaType><con:status>200</con:status><con:params/><con:element>Response</con:element></con:representation><con:representation type="REQUEST"><con:mediaType>application/json</con:mediaType><con:params/></con:representation><con:representation type="FAULT"><con:mediaType>application/json</con:mediaType><con:status>405 400</con:status><con:params/><con:element xmlns:pet="https://petstore.swagger.io/v2/pet/">pet:Fault</con:element></con:representation><con:representation type="FAULT"><con:mediaType>application/xml</con:mediaType><con:status>405</con:status><con:params/><con:element>apiResponse</con:element></con:representation><con:request name="Request 1" id="4a433243-e5b6-4848-936b-60c4a4486ce1" mediaType="application/json" postQueryString="false"><con:settings><con:setting id="com.eviware.soapui.impl.wsdl.WsdlRequest@request-headers">&lt;xml-fragment/></con:setting></con:settings><con:endpoint>https://petstore.swagger.io</con:endpoint><con:request/><con:originalUri>https://petstore.swagger.io/v2/pet/findByStatus</con:originalUri><con:credentials><con:selectedAuthProfile>No Authorization</con:selectedAuthProfile><con:authType>No Authorization</con:authType></con:credentials><con:jmsConfig JMSDeliveryMode="PERSISTENT"/><con:jmsPropertyConfig/><con:parameters><con:entry key="status" value="sold"/></con:parameters><con:parameterOrder><con:entry>status</con:entry></con:parameterOrder></con:request></con:method></con:resource></con:interface><con:testSuite id="3bbd129d-6a29-40c5-a146-3ed54ff1bc84" name="TestSuite 1"><con:settings/><con:savedRecentRuns>1</con:savedRecentRuns><con:runType>SEQUENTIAL</con:runType><con:testCase id="23a1edc2-91ac-48b9-a352-907913193efd" failOnError="true" failTestCaseOnErrors="true" keepSession="false" maxResults="0" name="TestCase 1" searchProperties="true"><con:settings/><con:testStep type="datasource" name="DataSource" id="367c742b-0a37-411c-a9c2-e6ad16178855"><con:settings><con:setting id="com.eviware.soapui.impl.wsdl.teststeps.datasource.DataSourceContainer@prepared-properties">&lt;xml-fragment/></con:setting></con:settings><con:config xsi:type="con:DataSourceStep" xmlns:xsi="http://www.w3.org/2001/XMLSchema-instance"><con:dataSource type="JDBC"><con:configuration><driver>com.mysql.jdbc.Driver</driver><connstr>jdbc:mysql://db4free.net:3306/soapuitesting?user=soapuiuser&amp;password=PASS_VALUE</connstr><pass>soapuipassword</pass><Connection>Jdbc Req</Connection><query>Select *
From petStore</query><fetchSize/><stored-procedure>false</stored-procedure></con:configuration></con:dataSource><con:shared>true</con:shared><con:restartShared>true</con:restartShared><con:property>petID</con:property><con:property>petName</con:property><con:property>petStatus</con:property><con:completeLastOperation>true</con:completeLastOperation><con:restartOnRun>true</con:restartOnRun></con:config></con:testStep><con:testStep type="restrequest" name="Pet Get" id="8f29e0c1-2c85-4665-a5ef-4782768315db"><con:settings/><con:config service="https://petstore.swagger.io" resourcePath="/v2/pet/" methodName="Pet 1" xsi:type="con:RestRequestStep" xmlns:xsi="http://www.w3.org/2001/XMLSchema-instance"><con:restRequest name="Pet Get" id="4a433243-e5b6-4848-936b-60c4a4486ce1" mediaType="application/json" postQueryString="false"><con:settings><con:setting id="com.eviware.soapui.impl.wsdl.WsdlRequest@request-headers">&lt;xml-fragment/></con:setting></con:settings><con:endpoint>https://petstore.swagger.io</con:endpoint><con:request/><con:originalUri>https://petstore.swagger.io/v2/pet/findByStatus</con:originalUri><con:assertion type="Valid HTTP Status Codes" id="99317543-b6ca-482b-a4f9-a4dba4350ebc" name="Valid HTTP Status Codes"><con:settings/><con:configuration><codes>200</codes></con:configuration></con:assertion><con:assertion type="Response SLA Assertion" id="ab9a97d8-66ab-462b-96eb-657192b7e98f" name="Response SLA"><con:configuration><SLA>200</SLA></con:configuration></con:assertion><con:credentials><con:selectedAuthProfile>No Authorization</con:selectedAuthProfile><con:authType>No Authorization</con:authType></con:credentials><con:jmsConfig JMSDeliveryMode="PERSISTENT"/><con:jmsPropertyConfig/><con:parameters><con:entry key="status" value="sold"/></con:parameters><con:parameterOrder><con:entry>status</con:entry></con:parameterOrder></con:restRequest></con:config></con:testStep><con:testStep type="restrequest" name="Pet Post" id="db5b77c0-47b8-4d78-b424-90efbe84ab7f"><con:settings/><con:config service="https://petstore.swagger.io" methodName="Pet 1" resourcePath="/v2/pet/" xsi:type="con:RestRequestStep" xmlns:xsi="http://www.w3.org/2001/XMLSchema-instance"><con:restRequest name="Pet Post" id="558f85c5-86c9-4d8d-b937-7d627a952ff9" mediaType="application/json" postQueryString="false"><con:settings><con:setting id="com.eviware.soapui.impl.wsdl.WsdlRequest@request-headers">&lt;xml-fragment/></con:setting></con:settings><con:encoding>UTF-8</con:encoding><con:endpoint>https://petstore.swagger.io</con:endpoint><con:request>{
	"id": 15518,
	"name": "AB Devilers",
	"status": "alive"
}</con:request><con:originalUri>https://petstore.swagger.io/v2/pet/</con:originalUri><con:assertion type="Valid HTTP Status Codes" id="28b12d6f-5299-4765-9e12-b63699c95f8d" name="Valid HTTP Status Codes"><con:settings/><con:configuration><codes>200</codes></con:configuration></con:assertion><con:assertion type="Response SLA Assertion" id="df7fa750-bacf-496f-a1eb-d5b9e09f1ffc" name="Response SLA"><con:configuration><SLA>200</SLA></con:configuration></con:assertion><con:credentials><con:selectedAuthProfile>No Authorization</con:selectedAuthProfile><con:authType>No Authorization</con:authType></con:credentials><con:jmsConfig JMSDeliveryMode="PERSISTENT"/><con:parameters/></con:restRequest></con:config></con:testStep><con:testStep type="datasourceloop" name="DataSource Loop" id="27ebb776-6d25-4050-bafe-fc48ff16c971"><con:settings/><con:config><dataSourceStep>DataSource</dataSourceStep><targetStep>Pet 1 - Request 1</targetStep><discardResults>true</discardResults></con:config></con:testStep><con:testStep type="datasink" name="DataSink" id="82a4c642-2b26-4e30-a98c-00b67c5fc960"><con:settings/><con:config xsi:type="con:DataSinkStep" xmlns:xsi="http://www.w3.org/2001/XMLSchema-instance"><con:dataSink type="Excel"><con:configuration><file/><outfile>C:/Alchemy/API/DataSinkOp/Result.xlsx</outfile><worksheet>DataSink</worksheet><cell>A1</cell><evaluateFormulas>false</evaluateFormulas><append>false</append></con:configuration></con:dataSink><con:properties><con:property><con:name>${Pet Get#Response}</con:name><con:value/></con:property></con:properties></con:config></con:testStep><con:properties/><con:reportParameters/><con:breakPoints><con:testStepId>367c742b-0a37-411c-a9c2-e6ad16178855</con:testStepId><con:status>NONE</con:status><con:properties/></con:breakPoints><con:breakPoints><con:testStepId>db5b77c0-47b8-4d78-b424-90efbe84ab7f</con:testStepId><con:status>NONE</con:status><con:properties/></con:breakPoints><con:breakPoints><con:testStepId>8f29e0c1-2c85-4665-a5ef-4782768315db</con:testStepId><con:status>NONE</con:status><con:properties/></con:breakPoints></con:testCase><con:testCase id="67f551d3-7bc9-4cad-96a2-19af14276355" discardOkResults="false" failOnError="true" failTestCaseOnErrors="true" keepSession="false" name="TestCase 2" searchProperties="true" timeout="0" maxResults="0"><con:settings/><con:savedRecentRuns>1</con:savedRecentRuns><con:testStep type="jdbc" name="JDBC Request" id="43c9bcdd-11b1-474b-8fbe-1e5e0d8ce705"><con:settings><con:setting id="prettyPrintResponse">true</con:setting></con:settings><con:config xsi:type="con:JdbcRequestTestStep" convertColumnNamesToUpperCase="true" xmlns:xsi="http://www.w3.org/2001/XMLSchema-instance"><con:dbConnectionName>Jdbc Req</con:dbConnectionName><con:driver>com.mysql.jdbc.Driver</con:driver><con:connectionString>jdbc:mysql://db4free.net:3306/soapuitesting?user=soapuiuser&amp;password=PASS_VALUE</con:connectionString><con:password>soapuipassword</con:password><con:connectionProperties/><con:query>SELECT * FROM petData</con:query><con:properties/></con:config></con:testStep><con:properties/><con:reportParameters/></con:testCase><con:properties/><con:reportParameters/></con:testSuite><con:properties/><con:wssContainer/><con:databaseConnectionContainer><con:databaseConnection><con:name>Jdbc Req</con:name><con:driver xmlns:xsi="http://www.w3.org/2001/XMLSchema-instance">com.mysql.jdbc.Driver</con:driver><con:connectionString xmlns:xsi="http://www.w3.org/2001/XMLSchema-instance">jdbc:mysql://db4free.net:3306/soapuitesting?user=soapuiuser&amp;password=PASS_VALUE</con:connectionString><con:password>soapuipassword</con:password><con:connectionProperties/></con:databaseConnection></con:databaseConnectionContainer><con:jmsConnectionContainer/><con:oAuth2ProfileContainer/><con:oAuth1ProfileContainer/><con:reporting><con:xmlTemplates/><con:parameters/></con:reporting><con:authRepository/><con:tags/></con:soapui-project>